shamsidate/__init__.py
shamsidate/shamsi.py
ShamsiDate-1.0.2.dist-info/LICENSE
ShamsiDate-1.0.2.dist-info/METADATA
ShamsiDate-1.0.2.dist-info/WHEEL
ShamsiDate-1.0.2.dist-info/entry_points.txt
ShamsiDate-1.0.2.dist-info/top_level.txt
ShamsiDate-1.0.2.dist-info/RECORD
