Metadata-Version: 2.1
Name: ShamsiDate
Version: 1.0.2
Summary: Convert Shamsi to Gregorian date and vice versa
Home-page: https://gitlab.com/samic130/shamsi/
Author: Samic
Author-email: shamsi@samic.org
License: GPLv3
Project-URL: Bug Tracker, https://gitlab.com/samic130/shamsi/-/issues
Platform: UNKNOWN
Classifier: Programming Language :: Python :: 3
Classifier: License :: OSI Approved :: GNU General Public License v3 (GPLv3)
Classifier: Operating System :: OS Independent
Requires-Python: >=3.0
License-File: LICENSE
